fenrircore/__init__.py
fenrircore/__main__.py
fenrircore/arper.py
fenrircore/fenrir.py
fenrircore/filehandler.py
fenrircore/firewall.py
fenrircore/getmacvendors.py
fenrircore/scanner.py
fenrircore/vpn.py
fenrircore-0.7.0.dist-info/LICENSE
fenrircore-0.7.0.dist-info/METADATA
fenrircore-0.7.0.dist-info/WHEEL
fenrircore-0.7.0.dist-info/entry_points.txt
fenrircore-0.7.0.dist-info/top_level.txt
fenrircore-0.7.0.dist-info/RECORD
