Metadata-Version: 2.1
Name: fenrircore
Version: 0.7.0
Summary: use Fenrir to route configured network devices trough configured VPN tunnel
Project-URL: Source, https://github.com/HannesHofer/fenrir
Project-URL: Tracker, https://github.com/HannesHofer/fenrir/issues
License-File: LICENSE
Requires-Dist: pycryptodomex
Requires-Dist: pyroute2
Requires-Dist: python-iptables
Requires-Dist: requests
Requires-Dist: scapy
